{
  "$schema": "https://ui.shadcn.com/schema/registry-item.json",
  "name": "pricing-v1-demo",
  "type": "registry:block",
  "description": "A Pricing Demo of three section.",
  "dependencies": [
    "lucide-react"
  ],
  "registryDependencies": [
    "card",
    "utils",
    "button"
  ],
  "files": [
    {
      "path": "registry/demo/blocks/pricing-v1-demo.tsx",
      "content": "import PricingCard from \"@/registry/blocks/pricing-v1\";\r\n\r\nexport default function PricingV1Demo() {\r\n  const pricingPlans = [\r\n    {\r\n      id: \"startup\",\r\n      name: \"Startup\",\r\n      time: \"2 weeks\",\r\n      prices: \"₹25,000/- | $299\",\r\n      features: [\r\n        \"15–20s Animation (1-2 SKUs)\",\r\n        \"Basic storyboard design\",\r\n        \"Delivered in 2 weeks\",\r\n        \"Standard quality rendering\",\r\n        \"1 revision included\",\r\n        \"Email support\",\r\n      ],\r\n      description:\r\n        \"Perfect for small businesses starting their video marketing journey\",\r\n    },\r\n    {\r\n      id: \"pro\",\r\n      name: \"Professional\",\r\n      time: \"3 weeks\",\r\n      prices: \"₹55,000/- | $699\",\r\n      features: [\r\n        \"20–30s Animation (up to 3 SKUs)\",\r\n        \"Professional storyboard + design\",\r\n        \"Delivered in 3 weeks\",\r\n        \"High-quality rendering\",\r\n        \"Up to 2 revisions\",\r\n        \"Priority email support\",\r\n        \"Custom transitions\",\r\n      ],\r\n      description:\r\n        \"Ideal for growing businesses that need professional quality\",\r\n      isPopular: true,\r\n    },\r\n    {\r\n      id: \"premium\",\r\n      name: \"Premium\",\r\n      time: \"4 weeks\",\r\n      prices: \"₹1,70,500/- | $2,049\",\r\n      discount: \"Save Flat ₹1,500/- | Save $20\",\r\n      features: [\r\n        \"30–40s Animation (up to 5 SKUs)\",\r\n        \"Advanced storyboard + shot design\",\r\n        \"Delivered in 4 weeks\",\r\n        \"Lighting, Camera Animation, Depth effects\",\r\n        \"Up to 3 structured revisions\",\r\n        \"3D Modelling - Included\",\r\n        \"Dedicated project manager\",\r\n        \"Priority support with video calls\",\r\n      ],\r\n      description:\r\n        \"Enterprise-grade solution with premium features and dedicated support\",\r\n    },\r\n  ];\r\n\r\n  return (\r\n    <div className=\"grid md:grid-cols-3 gap-8 px-10 py-20\">\r\n      {pricingPlans.map((plan) => (\r\n        <PricingCard\r\n          {...plan}\r\n          key={plan.id}\r\n          className={\r\n            plan.isPopular ? \"ring-2 ring-yellow-500/50 scale-105\" : \"\"\r\n          }\r\n        />\r\n      ))}\r\n    </div>\r\n  );\r\n}\r\n",
      "type": "registry:block",
      "target": "app/page.tsx"
    },
    {
      "path": "registry/blocks/pricing-v1.tsx",
      "content": "import { Card, CardContent, CardFooter, CardHeader } from \"@/components/ui/card\";\r\nimport { Button } from \"@/components/ui/button\";\r\nimport { CheckCircle2 } from \"lucide-react\";\r\nimport { cn } from \"@/lib/utils\";\r\n\r\nconst ACCENT = \"#C6FF3A\";\r\n\r\ninterface PricingCardProps {\r\n  id: string;\r\n  name: string;\r\n  time: string;\r\n  prices: string;\r\n  discount?: string;\r\n  features: string[];\r\n  className?: string;\r\n  isPopular?: boolean;\r\n  description?: string;\r\n}\r\n\r\nexport default function PricingCard({\r\n  name,\r\n  time,\r\n  prices,\r\n  features,\r\n  discount,\r\n  isPopular,\r\n  className,\r\n  description,\r\n}: PricingCardProps) {\r\n  return (\r\n    <Card\r\n      className={cn(\r\n        \"relative overflow-hidden rounded-2xl bg-gradient-to-br from-gray-900 to-gray-800 shadow-2xl transition-all duration-300 flex flex-col justify-between h-full\",\r\n        className\r\n      )}\r\n    >\r\n      {isPopular && (\r\n        <div className=\"absolute -right-8 top-4 rotate-45 bg-gradient-to-r from-yellow-400 to-orange-500 px-8 py-1 text-xs font-bold text-black z-10\">\r\n          POPULAR\r\n        </div>\r\n      )}\r\n\r\n      <div>\r\n        <CardHeader>\r\n          <h4 className=\"text-lg font-semibold tracking-wide text-gray-100 mb-2\">\r\n            {name}\r\n          </h4>\r\n\r\n          <div className=\"mb-4\">\r\n            <span className=\"text-2xl font-bold text-white\">{prices}</span>\r\n            <span className=\"text-sm text-gray-400 ml-2\">per video</span>\r\n          </div>\r\n\r\n          {discount && (\r\n            <div className=\"text-green-400 font-medium text-sm mb-4\">\r\n              {discount}\r\n            </div>\r\n          )}\r\n\r\n          <div className=\"flex gap-2 mb-4\">\r\n            <Button\r\n              className=\"flex-1 text-sm\"\r\n              style={{\r\n                backgroundColor: \"#1a1a1a\",\r\n                color: \"#ffffff\",\r\n                border: \"1px solid #333\",\r\n              }}\r\n            >\r\n              View Example\r\n            </Button>\r\n\r\n            <Button\r\n              className=\"flex-1 text-sm\"\r\n              style={{\r\n                backgroundColor: ACCENT,\r\n                color: \"#000\",\r\n              }}\r\n            >\r\n              Delivery: {time}\r\n            </Button>\r\n          </div>\r\n        </CardHeader>\r\n\r\n        <CardContent>\r\n          {description && (\r\n            <p className=\"mb-4 text-sm text-gray-300\">{description}</p>\r\n          )}\r\n\r\n          <ul className=\"space-y-3\">\r\n            {features?.map((feature, i) => (\r\n              <li key={i} className=\"flex items-start gap-3\">\r\n                <CheckCircle2\r\n                  className=\"mt-0.5 h-4 w-4 flex-shrink-0\"\r\n                  style={{ color: ACCENT }}\r\n                />\r\n                <span className=\"text-sm text-gray-200\">{feature}</span>\r\n              </li>\r\n            )) ?? null}\r\n          </ul>\r\n        </CardContent>\r\n      </div>\r\n\r\n      <CardFooter>\r\n        <Button\r\n          className=\"w-full font-semibold\"\r\n          size=\"lg\"\r\n          style={{\r\n            backgroundColor: ACCENT,\r\n            color: \"#000\",\r\n          }}\r\n        >\r\n          Select Plan\r\n        </Button>\r\n      </CardFooter>\r\n    </Card>\r\n  );\r\n}\r\n",
      "type": "registry:block",
      "target": "components/pricing-v1.tsx"
    }
  ],
  "categories": [
    "pricing"
  ]
}