{
  "$schema": "https://ui.shadcn.com/schema/registry-item.json",
  "name": "paper-background",
  "type": "registry:component",
  "files": [
    {
      "path": "registry/components/paper-background.tsx",
      "content": "import { cn } from \"@/lib/utils\";\r\n\r\nexport default function PaperBackground({\r\n  className,\r\n}: React.ComponentProps<\"div\">) {\r\n  return (\r\n    <div\r\n      className={cn(\r\n        \"absolute inset-0 bg-background dark:bg-black overflow-hidden\",\r\n        className\r\n      )}\r\n    >\r\n      <svg\r\n        className=\"absolute\"\r\n        viewBox=\"0 0 1000 800\"\r\n        fill=\"none\"\r\n        xmlns=\"http://www.w3.org/2000/svg\"\r\n      >\r\n        <defs>\r\n          <filter\r\n            id=\"heroTextBlur\"\r\n            x=\"-50%\"\r\n            y=\"-50%\"\r\n            width=\"250%\"\r\n            height=\"200%\"\r\n          >\r\n            <feGaussianBlur stdDeviation=\"12\" result=\"blur\" />\r\n            <feTurbulence baseFrequency=\"0.7\" numOctaves=\"4\" result=\"noise\" />\r\n\r\n            <feComponentTransfer in=\"monoNoise\" result=\"alphaAdjustedNoise\">\r\n              <feFuncA type=\"discrete\" tableValues=\"0.03 0.06 0.09 0.12\" />\r\n            </feComponentTransfer>\r\n          </filter>\r\n        </defs>\r\n\r\n        <g>\r\n          <ellipse\r\n            cx=\"300\"\r\n            cy=\"350\"\r\n            rx=\"400\"\r\n            ry=\"200\"\r\n            filter=\"url(#heroTextBlur)\"\r\n            opacity=\"0.5\"\r\n          />\r\n          <ellipse\r\n            cx=\"350\"\r\n            cy=\"320\"\r\n            rx=\"500\"\r\n            ry=\"250\"\r\n            filter=\"url(#heroTextBlur)\"\r\n            opacity=\"0.4\"\r\n          />\r\n          <ellipse\r\n            cx=\"400\"\r\n            cy=\"300\"\r\n            rx=\"600\"\r\n            ry=\"300\"\r\n            filter=\"url(#heroTextBlur)\"\r\n            opacity=\"0.2\"\r\n          />\r\n        </g>\r\n      </svg>\r\n    </div>\r\n  );\r\n}\r\n",
      "type": "registry:component"
    }
  ]
}